my_own_package/__init__.py
primul_pachet_Iustin_Muresanu-0.1.0.dist-info/METADATA
primul_pachet_Iustin_Muresanu-0.1.0.dist-info/WHEEL
primul_pachet_Iustin_Muresanu-0.1.0.dist-info/top_level.txt
primul_pachet_Iustin_Muresanu-0.1.0.dist-info/RECORD
