Metadata-Version: 2.1
Name: primul-pachet-Iustin-Muresanu
Version: 0.1.0
Summary: primul meu pachet
Author: Iustin Muresanu
